v_bootstrap/__init__.py
v_bootstrap/onboard/__init__.py
v_bootstrap/onboard/board.py
v_bootstrap/onboard/boot.py
v_bootstrap/utils/__init__.py
v_bootstrap/utils/connectors.py
v_bootstrap/utils/errors.py
v_bootstrap/utils/logs.py
v_bootstrap/utils/security.py
v_bootstrap-1.5.1.dist-info/METADATA
v_bootstrap-1.5.1.dist-info/WHEEL
v_bootstrap-1.5.1.dist-info/entry_points.txt
v_bootstrap-1.5.1.dist-info/top_level.txt
v_bootstrap-1.5.1.dist-info/RECORD
